chinese_slugify/__init__.py
chinese_slugify/main.py
chinese_slugify-0.1.2.dist-info/METADATA
chinese_slugify-0.1.2.dist-info/WHEEL
chinese_slugify-0.1.2.dist-info/top_level.txt
chinese_slugify-0.1.2.dist-info/RECORD
